QcureUi/CloseWindow.py
QcureUi/Titlebar.py
QcureUi/WindowWithTitleBar.py
QcureUi/__init__.py
QcureUi/cure.py
QcureUi/qss_getter.py
QcureUi/resourse_cfg.py
QcureUi/simple_qss.py
QcureUi/beautifyUi/theme.json
QcureUi/beautifyUi/blue/checkbox_down.png
QcureUi/beautifyUi/blue/checkbox_hoverCheck.png
QcureUi/beautifyUi/blue/checkbox_hoverUncheck.png
QcureUi/beautifyUi/blue/checkbox_normal.png
QcureUi/beautifyUi/blue/close.png
QcureUi/beautifyUi/blue/closehover.png
QcureUi/beautifyUi/blue/closepress.png
QcureUi/beautifyUi/blue/down_arrow.png
QcureUi/beautifyUi/blue/minsize.png
QcureUi/beautifyUi/blue/minsizehover.png
QcureUi/beautifyUi/blue/minsizepress.png
QcureUi/beautifyUi/blue/radio_down.png
QcureUi/beautifyUi/blue/radio_hoverCheck.png
QcureUi/beautifyUi/blue/radio_hoverUncheck.png
QcureUi/beautifyUi/blue/radio_normal.png
QcureUi/beautifyUi/blue/resize.png
QcureUi/beautifyUi/blue/resizehover.png
QcureUi/beautifyUi/blue/resizepress.png
QcureUi/beautifyUi/blue/retsize.png
QcureUi/beautifyUi/blue/retsizehover.png
QcureUi/beautifyUi/blue/retsizepress.png
QcureUi/beautifyUi/blueDeep/checkbox_down.png
QcureUi/beautifyUi/blueDeep/checkbox_hoverCheck.png
QcureUi/beautifyUi/blueDeep/checkbox_hoverUncheck.png
QcureUi/beautifyUi/blueDeep/checkbox_normal.png
QcureUi/beautifyUi/blueDeep/close.png
QcureUi/beautifyUi/blueDeep/closehover.png
QcureUi/beautifyUi/blueDeep/closepress.png
QcureUi/beautifyUi/blueDeep/down_arrow.png
QcureUi/beautifyUi/blueDeep/minsize.png
QcureUi/beautifyUi/blueDeep/minsizehover.png
QcureUi/beautifyUi/blueDeep/minsizepress.png
QcureUi/beautifyUi/blueDeep/radio_down.png
QcureUi/beautifyUi/blueDeep/radio_hoverCheck.png
QcureUi/beautifyUi/blueDeep/radio_hoverUncheck.png
QcureUi/beautifyUi/blueDeep/radio_normal.png
QcureUi/beautifyUi/blueDeep/resize.png
QcureUi/beautifyUi/blueDeep/resizehover.png
QcureUi/beautifyUi/blueDeep/resizepress.png
QcureUi/beautifyUi/blueDeep/retsize.png
QcureUi/beautifyUi/blueDeep/retsizehover.png
QcureUi-0.0.3.dist-info/LICENSE
QcureUi-0.0.3.dist-info/METADATA
QcureUi-0.0.3.dist-info/WHEEL
QcureUi-0.0.3.dist-info/top_level.txt
QcureUi-0.0.3.dist-info/RECORD
