Metadata-Version: 2.1
Name: QcureUi
Version: 0.0.3
Summary: Used for pyqt5 beautification
Home-page: https://github.com/pypa/sampleproject
Author: Lux
Author-email: 1223411083@qq.com
License: UNKNOWN
Project-URL: Blog, https://blog.csdn.net/qq_45414559/article/details/105560090
Platform: UNKNOWN
Classifier: Programming Language :: Python :: 3
Classifier: License :: OSI Approved :: MIT License
Classifier: Operating System :: OS Independent
Requires-Dist: pywin32
